LICENSE
MANIFEST.in
README.md
setup.py
iniconfig/__init__.py
iniconfig/iniconfig.py
iniconfig.py.egg-info/PKG-INFO
iniconfig.py.egg-info/SOURCES.txt
iniconfig.py.egg-info/dependency_links.txt
iniconfig.py.egg-info/top_level.txt
tests/__init__.py
tests/iniconfig_test.py