Metadata-Version: 1.1
Name: iniconfig.py
Version: 1.0.3
Summary: A more convenient and practical approach to manage .ini files
Home-page: https://github.com/dmiro/iniconfig
Author: David Miro
Author-email: lite.3engine@gmail.com
License: The MIT License (MIT)
